odoo/addons/multi_step_wizard/README.rst
odoo/addons/multi_step_wizard/__init__.py
odoo/addons/multi_step_wizard/__manifest__.py
odoo/addons/multi_step_wizard/i18n/es_ES.po
odoo/addons/multi_step_wizard/i18n/multi_step_wizard.pot
odoo/addons/multi_step_wizard/models/__init__.py
odoo/addons/multi_step_wizard/models/multi_step_wizard.py
odoo/addons/multi_step_wizard/static/description/icon.png
odoo/addons/multi_step_wizard/tests/__init__.py
odoo/addons/multi_step_wizard/tests/multi_step_wizard_test.py
odoo/addons/multi_step_wizard/tests/test_multi_step_wizard.py
odoo/addons/multi_step_wizard/views/multi_step_wizard_views.xml
odoo11_addon_multi_step_wizard-11.0.1.1.1.dist-info/METADATA
odoo11_addon_multi_step_wizard-11.0.1.1.1.dist-info/WHEEL
odoo11_addon_multi_step_wizard-11.0.1.1.1.dist-info/top_level.txt
odoo11_addon_multi_step_wizard-11.0.1.1.1.dist-info/RECORD
